vconfig.py
vconfig-0.1.2.dist-info/LICENSE
vconfig-0.1.2.dist-info/METADATA
vconfig-0.1.2.dist-info/WHEEL
vconfig-0.1.2.dist-info/top_level.txt
vconfig-0.1.2.dist-info/RECORD
